README.rst
setup.cfg
setup.py
ldrand/__init__.py
ldrand/cli.py
ldrand/linker.py
ldrand/util.py
ldrand.egg-info/PKG-INFO
ldrand.egg-info/SOURCES.txt
ldrand.egg-info/dependency_links.txt
ldrand.egg-info/entry_points.txt
ldrand.egg-info/top_level.txt