Metadata-Version: 1.1
Name: ldrand
Version: 0.42
Summary: Link order randomizing linker wrapper
Home-page: https://github.com/parttimenerd/ldrand
Author: Johannes Bechberger
Author-email: me@mostlynerdless.de
License: GPLv3
Platform: linux
Classifier: Programming Language :: Python :: 3.6
Classifier: Programming Language :: Python :: 3.7
Classifier: Programming Language :: Python :: 3.8
Classifier: Programming Language :: Python :: 3 :: Only
Classifier: Operating System :: POSIX :: Linux
Classifier: Topic :: System :: Benchmark
Classifier: License :: OSI Approved :: GNU General Public License v3 or later (GPLv3+)
Classifier: Development Status :: 4 - Beta
Classifier: Environment :: Console
Classifier: Intended Audience :: Developers
